examples
flask_ripozo
flask_ripozo_tests
profiling
