Metadata-Version: 1.1
Name: flask-ripozo
Version: 1.0.4
Summary: An extension for ripozo and that brings HATEOAS/REST/Hypermedia apis to flask
Home-page: http://flask-ripozo.readthedocs.org/
Author: Tim Martin
Author-email: tim.martin@vertical-knowledge.com
License: UNKNOWN
Platform: UNKNOWN
Classifier: Development Status :: 3 - Alpha
Classifier: License :: Other/Proprietary License
Classifier: License :: OSI Approved :: GNU General Public License v2 (GPLv2)
Classifier: Programming Language :: Python
Classifier: Programming Language :: Python :: 2
Classifier: Programming Language :: Python :: 2.6
Classifier: Programming Language :: Python :: 2.7
Classifier: Programming Language :: Python :: 3
Classifier: Programming Language :: Python :: 3.3
Classifier: Programming Language :: Python :: 3.4
Classifier: Programming Language :: Python :: Implementation :: PyPy
Classifier: Topic :: Software Development :: Libraries :: Python Modules
